3_stage_pipeline/RTL/alu3_pipeline.sv
// alu3_pipeline - 3-stage synchronous pipelined ALU (easy concept).
//
// Pipeline stages (one register stage each):
//   STAGE 1  REG   : capture operands a, b, opcode + valid bit
//   STAGE 2  EX    : combinational ALU executes, result captured in reg
//   STAGE 3  WB    : writeback register drives the outputs
//
// Latency: valid_out asserts exactly 3 clock cycles after valid_in.
// Operations (op):
//   000  ADD   result = a + b
//   001  SUB   result = a - b
//   010  AND   result = a & b
//   011  OR    result = a | b
//   100  XOR   result = a ^ b
//   101  SLT   result = (a < b) ? 1 : 0        (signed compare)
//   110  SLL   result = a << b[4:0]
//   111  SRL   result = a >> b[4:0]            (logical)

module alu3_pipeline #(
    parameter int DATA_W = 32
)(
    input  logic                     clk,
    input  logic                     rst_n,
    input  logic                     valid_in,
    input  logic [DATA_W-1:0]        a,
    input  logic [DATA_W-1:0]        b,
    input  logic [2:0]               op,
    output logic                     valid_out,
    output logic [DATA_W-1:0]        result
);

    // =================================================================
    // STAGE 1 - operand register
    // =================================================================
    logic [DATA_W-1:0] a1;
    logic [DATA_W-1:0] b1;
    logic [2:0]        op1;
    logic              v1;

    always_ff @(posedge clk or negedge rst_n) begin
        if (!rst_n) begin
            a1  <= '0;
            b1  <= '0;
            op1 <= '0;
            v1  <= 1'b0;
        end else begin
            a1  <= a;
            b1  <= b;
            op1 <= op;
            v1  <= valid_in;
        end
    end

    // =================================================================
    // STAGE 2 - ALU execute (combinational logic in the pipeline)
    // =================================================================
    logic [DATA_W-1:0] alu_out;

    always_comb begin
        unique case (op1)
            3'b000: alu_out = a1 + b1;                         // ADD
            3'b001: alu_out = a1 - b1;                         // SUB
            3'b010: alu_out = a1 & b1;                         // AND
            3'b011: alu_out = a1 | b1;                         // OR
            3'b100: alu_out = a1 ^ b1;                         // XOR
            3'b101: alu_out = {31'b0, ($signed(a1) < $signed(b1))}; // SLT
            3'b110: alu_out = a1 << (b1[4:0]);                 // SLL
            default: alu_out = a1 >> (b1[4:0]);                // SRL
        endcase
    end

    logic [DATA_W-1:0] r2;
    logic              v2;

    always_ff @(posedge clk or negedge rst_n) begin
        if (!rst_n) begin
            r2 <= '0;
            v2 <= 1'b0;
        end else begin
            r2 <= alu_out;
            v2 <= v1;
        end
    end

    // =================================================================
    // STAGE 3 - writeback register
    // =================================================================
    always_ff @(posedge clk or negedge rst_n) begin
        if (!rst_n) begin
            result    <= '0;
            valid_out <= 1'b0;
        end else begin
            result    <= r2;
            valid_out <= v2;
        end
    end

endmodule

3_stage_pipeline/Sim/tb_alu3_pipeline.sv
// Self-checking testbench for the 3-stage pipelined ALU (alu3_pipeline).
// Usage: tclsh scripts/sim.tcl   (iverilog + vvp, writes tb_alu3_pipeline.vcd)
//
// The reference model mirrors the RTL stage by stage (REG -> EX -> WB) and
// compares result / valid_out on every clock edge after reset.

module tb_alu3_pipeline;

    localparam int DATA_W = 32;
    localparam int N_CHECKS = 200;

    logic clk = 0;
    logic rst_n = 0;
    logic valid_in = 0;
    logic [DATA_W-1:0] a;
    logic [DATA_W-1:0] b;
    logic [2:0]        op;
    logic valid_out;
    logic [DATA_W-1:0] result;

    alu3_pipeline #(
        .DATA_W(DATA_W)
    ) dut (
        .clk(clk),
        .rst_n(rst_n),
        .valid_in(valid_in),
        .a(a),
        .b(b),
        .op(op),
        .valid_out(valid_out),
        .result(result)
    );

    always #5 clk = ~clk;

    // ---------------------------------------------------------------
    //  Reference model: mirrors the RTL's 3 register stages exactly
    // ---------------------------------------------------------------
    logic [DATA_W-1:0] a1_ref;
    logic [DATA_W-1:0] b1_ref;
    logic [2:0]        op1_ref;
    logic              v1_ref;

    logic [DATA_W-1:0] alu_out_ref;
    logic [DATA_W-1:0] r2_ref;
    logic              v2_ref;

    logic [DATA_W-1:0] result_ref;
    logic              valid_out_ref;

    always_comb begin
        case (op1_ref)
            3'b000: alu_out_ref = a1_ref + b1_ref;
            3'b001: alu_out_ref = a1_ref - b1_ref;
            3'b010: alu_out_ref = a1_ref & b1_ref;
            3'b011: alu_out_ref = a1_ref | b1_ref;
            3'b100: alu_out_ref = a1_ref ^ b1_ref;
            3'b101: alu_out_ref = {31'b0, ($signed(a1_ref) < $signed(b1_ref))};
            3'b110: alu_out_ref = a1_ref << (b1_ref[4:0]);
            default: alu_out_ref = a1_ref >> (b1_ref[4:0]);
        endcase
    end

    // STAGE 1
    always_ff @(posedge clk or negedge rst_n) begin
        if (!rst_n) begin
            a1_ref  <= '0;
            b1_ref  <= '0;
            op1_ref <= '0;
            v1_ref  <= 1'b0;
        end else begin
            a1_ref  <= a;
            b1_ref  <= b;
            op1_ref <= op;
            v1_ref  <= valid_in;
        end
    end

    // STAGE 2
    always_ff @(posedge clk or negedge rst_n) begin
        if (!rst_n) begin
            r2_ref <= '0;
            v2_ref <= 1'b0;
        end else begin
            r2_ref <= alu_out_ref;
            v2_ref <= v1_ref;
        end
    end

    // STAGE 3
    always_ff @(posedge clk or negedge rst_n) begin
        if (!rst_n) begin
            result_ref    <= '0;
            valid_out_ref <= 1'b0;
        end else begin
            result_ref    <= r2_ref;
            valid_out_ref <= v2_ref;
        end
    end

    // ---------------------------------------------------------------
    //  Stimulus + checking
    // ---------------------------------------------------------------
    int errors = 0;
    int nchecks = 0;

    initial begin
        $dumpfile("tb_alu3_pipeline.vcd");
        $dumpvars(0, tb_alu3_pipeline);

        a  = '0;
        b  = '0;
        op = '0;

        // reset
        rst_n = 0;
        valid_in = 0;
        repeat (3) @(posedge clk);

        @(negedge clk);
        rst_n = 1;
        valid_in = 1;

        for (int i = 0; i < N_CHECKS; i++) begin
            @(negedge clk);
            a  = $random;
            b  = $random;
            op = 3'($unsigned($random) % 8);

            @(posedge clk);
            #1;

            if (valid_out !== valid_out_ref) begin
                $display("  [t=%0t] valid_out mismatch: DUT=%0b REF=%0b",
                         $time, valid_out, valid_out_ref);
                errors++;
            end
            if (result !== result_ref) begin
                $display("  [t=%0t] result mismatch: DUT=%0d REF=%0d (op=%0b a=%0d b=%0d)",
                         $time, result, result_ref, op1_ref, a1_ref, b1_ref);
                errors++;
            end
            nchecks++;
        end

        @(negedge clk);
        valid_in = 0;

        if (errors == 0)
            $display("SIM PASS: %0d outputs checked", nchecks);
        else
            $display("SIM FAIL: %0d errors out of %0d outputs checked", errors, nchecks);
        $finish;
    end

endmodule

3_stage_pipeline/Outputs/Sim/tb_alu3_pipeline.vcd
$date
	Thu Aug 13 14:28:39 2026
$end
$version
	Icarus Verilog
$end
$timescale
	1s
$end
$scope module tb_alu3_pipeline $end
$var wire 1 ! valid_out $end
$var wire 32 " result [31:0] $end
$var parameter 32 # DATA_W $end
$var parameter 32 $ N_CHECKS $end
$var reg 32 % a [31:0] $end
$var reg 32 & a1_ref [31:0] $end
$var reg 32 ' alu_out_ref [31:0] $end
$var reg 32 ( b [31:0] $end
$var reg 32 ) b1_ref [31:0] $end
$var reg 1 * clk $end
$var reg 3 + op [2:0] $end
$var reg 3 , op1_ref [2:0] $end
$var reg 32 - r2_ref [31:0] $end
$var reg 32 . result_ref [31:0] $end
$var reg 1 / rst_n $end
$var reg 1 0 v1_ref $end
$var reg 1 1 v2_ref $end
$var reg 1 2 valid_in $end
$var reg 1 3 valid_out_ref $end
$var integer 32 4 errors [31:0] $end
$var integer 32 5 nchecks [31:0] $end
$scope module dut $end
$var wire 32 6 a [31:0] $end
$var wire 32 7 b [31:0] $end
$var wire 1 * clk $end
$var wire 3 8 op [2:0] $end
$var wire 1 / rst_n $end
$var wire 1 2 valid_in $end
$var parameter 32 9 DATA_W $end
$var reg 32 : a1 [31:0] $end
$var reg 32 ; alu_out [31:0] $end
$var reg 32 < b1 [31:0] $end
$var reg 3 = op1 [2:0] $end
$var reg 32 > r2 [31:0] $end
$var reg 32 ? result [31:0] $end
$var reg 1 @ v1 $end
$var reg 1 A v2 $end
$var reg 1 ! valid_out $end
$upscope $end
$scope begin $ivl_for_loop0 $end
$var integer 32 B i [31:0] $end
$upscope $end
$upscope $end
$enddefinitions $end
$comment Show the parameter values. $end
$dumpall
b100000 9
b11001000 $
b100000 #
$end
#0
$dumpvars
b0 B
xA
x@
bx ?
bx >
bx =
bx <
bx ;
bx :
b0 8
b0 7
b0 6
b0 5
b0 4
x3
02
x1
x0
0/
bx .
bx -
bx ,
b0 +
0*
bx )
b0 (
bx '
bx &
b0 %
bx "
x!
$end
#5
b0 ;
b0 '
0@
b0 =
b0 <
b0 :
0A
b0 >
0!
b0 "
b0 ?
00
b0 ,
b0 )
b0 &
01
b0 -
03
b0 .
1*
#10
0*
#15
1*
#20
0*
#25
1*
#30
12
1/
0*
#35
10
1@
1*
#40
b1 +
b1 8
b11000000100010010101111010000001 (
b11000000100010010101111010000001 7
b10010000101010011010100100100 %
b10010000101010011010100100100 6
0*
#45
b1010001100010111101011010100011 ;
b1010001100010111101011010100011 '
b1 =
b11000000100010010101111010000001 <
b10010000101010011010100100100 :
1A
b1 ,
b11000000100010010101111010000001 )
b10010000101010011010100100100 &
11
1*
#46
b1 B
b1 5
#50
b101 +
b101 8
b110101110010111101100001101 (
b110101110010111101100001101 7
b10110001111100000101011001100011 %
b10110001111100000101011001100011 6
0*
#55
b1 '
b1 ;
13
b1010001100010111101011010100011 -
b101 ,
b110101110010111101100001101 )
b10110001111100000101011001100011 &
1!
b1010001100010111101011010100011 >
b101 =
b110101110010111101100001101 <
b10110001111100000101011001100011 :
1*
#56
b10 B
b10 5
#60
b1 +
b1 8
b10001001001101110101001000010010 (
b10001001001101110101001000010010 7
b10110010110000101000010001100101 %
b10110010110000101000010001100101 6
0*
#65
b101001100010110011001001010011 ;
b101001100010110011001001010011 '
b1 =
b10001001001101110101001000010010 <
b10110010110000101000010001100101 :
b1 >
b1010001100010111101011010100011 "
b1010001100010111101011010100011 ?
b1 ,
b10001001001101110101001000010010 )
b10110010110000101000010001100101 &
b1 -
b1010001100010111101011010100011 .
1*
#66
b11 B
b11 5
#70
b101 +
b101 8
b111011001000111111000101110110 (
b111011001000111111000101110110 7
b110110101111100110100001101 %
b110110101111100110100001101 6
0*
#75
b1 '
b1 ;
b1 .
b101001100010110011001001010011 -
b101 ,
b111011001000111111000101110110 )
b110110101111100110100001101 &
b1 "
b1 ?
b101001100010110011001001010011 >
b101 =
b111011001000111111000101110110 <
b110110101111100110100001101 :
1*
#76
b100 B
b100 5
#80
b1 +
b1 8
b1000110001011011111011110001100 (
b1000110001011011111011110001100 7
b1110110110101000101011111101101 %
b1110110110101000101011111101101 6
0*
#85
b110000101001100110000001100001 ;
b110000101001100110000001100001 '
b1 =
b1000110001011011111011110001100 <
b1110110110101000101011111101101 :
b1 >
b101001100010110011001001010011 "
b101001100010110011001001010011 ?
b1 ,
b1000110001011011111011110001100 )
b1110110110101000101011111101101 &
b1 -
b101001100010110011001001010011 .
1*
#86
b101 B
b101 5
#90
b10 +
b10 8
b11100010111101111000010011000101 (
b11100010111101111000010011000101 7
b11100011001101110010010011000110 %
b11100011001101110010010011000110 6
0*
#95
b11100010001101110000010011000100 '
b11100010001101110000010011000100 ;
b1 .
b110000101001100110000001100001 -
b10 ,
b11100010111101111000010011000101 )
b11100011001101110010010011000110 &
b1 "
b1 ?
b110000101001100110000001100001 >
b10 =
b11100010111101111000010011000101 <
b11100011001101110010010011000110 :
1*
#96
b110 B
b110 5
#100
b10111011110100100111001001110111 (
b10111011110100100111001001110111 7
b1110010101011111111011111100101 %
b1110010101011111111011111100101 6
0*
#105
b110010100000100111001001100101 ;
b110010100000100111001001100101 '
b10111011110100100111001001110111 <
b1110010101011111111011111100101 :
b11100010001101110000010011000100 >
b110000101001100110000001100001 "
b110000101001100110000001100001 ?
b10111011110100100111001001110111 )
b1110010101011111111011111100101 &
b11100010001101110000010011000100 -
b110000101001100110000001100001 .
1*
#106
b111 B
b111 5
#110
b110 +
b110 8
b1111001001100000110100111110010 (
b1111001001100000110100111110010 7
b1000111111011001101101110001111 %
b1000111111011001101101110001111 6
0*
#115
b1101110001111000000000000000000 '
b1101110001111000000000000000000 ;
b11100010001101110000010011000100 .
b110010100000100111001001100101 -
b110 ,
b1111001001100000110100111110010 )
b1000111111011001101101110001111 &
b11100010001101110000010011000100 "
b11100010001101110000010011000100 ?
b110010100000100111001001100101 >
b110 =
b1111001001100000110100111110010 <
b1000111111011001101101110001111 :
1*
#116
b1000 B
b1000 5
#120
b100 +
b100 8
b11100010110010100100111011000101 (
b11100010110010100100111011000101 7
b11110100000000000111101011101000 %
b11110100000000000111101011101000 6
0*
#125
b10110110010100011010000101101 ;
b10110110010100011010000101101 '
b100 =
b11100010110010100100111011000101 <
b11110100000000000111101011101000 :
b1101110001111000000000000000000 >
b110010100000100111001001100101 "
b110010100000100111001001100101 ?
b100 ,
b11100010110010100100111011000101 )
b11110100000000000111101011101000 &
b1101110001111000000000000000000 -
b110010100000100111001001100101 .
1*
#126
b1001 B
b1001 5
#130
b101 +
b101 8
b10010110101010110101100000101101 (
b10010110101010110101100000101101 7
b11011110100011100010100010111101 %
b11011110100011100010100010111101 6
0*
#135
b0 '
b0 ;
b1101110001111000000000000000000 .
b10110110010100011010000101101 -
b101 ,
b10010110101010110101100000101101 )
b11011110100011100010100010111101 &
b1101110001111000000000000000000 "
b1101110001111000000000000000000 ?
b10110110010100011010000101101 >
b101 =
b10010110101010110101100000101101 <
b11011110100011100010100010111101 :
1*
#136
b1010 B
b1010 5
#140
b0 +
b0 8
b101011100111000011100001010 (
b101011100111000011100001010 7
b10110001111011110110001001100011 %
b10110001111011110110001001100011 6
0*
#145
b10110111011000101110100101101101 ;
b10110111011000101110100101101101 '
b0 =
b101011100111000011100001010 <
b10110001111011110110001001100011 :
b0 >
b10110110010100011010000101101 "
b10110110010100011010000101101 ?
b0 ,
b101011100111000011100001010 )
b10110001111011110110001001100011 &
b0 -
b10110110010100011010000101101 .
1*
#146
b1011 B
b1011 5
#150
b101 +
b101 8
b1010101011110000100010110101010 (
b1010101011110000100010110101010 7
b10000011001000010000100100000 %
b10000011001000010000100100000 6
0*
#155
b1 '
b1 ;
b0 .
b10110111011000101110100101101101 -
b101 ,
b1010101011110000100010110101010 )
b10000011001000010000100100000 &
b0 "
b0 ?
b10110111011000101110100101101101 >
b101 =
b1010101011110000100010110101010 <
b10000011001000010000100100000 :
1*
#156
b1100 B
b1100 5
#160
b10001001100000111011100000010011 (
b10001001100000111011100000010011 7
b11001011001000000011111010010110 %
b11001011001000000011111010010110 6
0*
#165
b0 ;
b0 '
b10001001100000111011100000010011 <
b11001011001000000011111010010110 :
b1 >
b10110111011000101110100101101101 "
b10110111011000101110100101101101 ?
b10001001100000111011100000010011 )
b11001011001000000011111010010110 &
b1 -
b10110111011000101110100101101101 .
1*
#166
b1101 B
b1101 5
#170
b110101100111111101110101101011 (
b110101100111111101110101101011 7
b10101001101001111101011001010011 %
b10101001101001111101011001010011 6
0*
#175
b1 '
b1 ;
b1 .
b0 -
b110101100111111101110101101011 )
b10101001101001111101011001010011 &
b1 "
b1 ?
b0 >
b110101100111111101110101101011 <
b10101001101001111101011001010011 :
1*
#176
b1110 B
b1110 5
#180
b11010111010101100011111010101110 (
b11010111010101100011111010101110 7
b10000001000101110100101000000010 %
b10000001000101110100101000000010 6
0*
#185
b11010111010101100011111010101110 <
b10000001000101110100101000000010 :
b1 >
b0 "
b0 ?
b11010111010101100011111010101110 )
b10000001000101110100101000000010 &
b1 -
b0 .
1*
#186
b1111 B
b1111 5
#190
b10 +
b10 8
b10001100001000100100100100011 (
b10001100001000100100100100011 7
b11100111110001010111001011001111 %
b11100111110001010111001011001111 6
0*
#195
b1100001000100000000000011 '
b1100001000100000000000011 ;
b1 .
b10 ,
b10001100001000100100100100011 )
b11100111110001010111001011001111 &
b1 "
b1 ?
b10 =
b10001100001000100100100100011 <
b11100111110001010111001011001111 :
1*
#196
b10000 B
b10000 5
#200
b10011110001100010100110000111100 (
b10011110001100010100110000111100 7
b11100101011100110000101011001010 %
b11100101011100110000101011001010 6
0*
#205
b10000100001100010000100000001000 ;
b10000100001100010000100000001000 '
b10011110001100010100110000111100 <
b11100101011100110000101011001010 :
b1100001000100000000000011 >
b10011110001100010100110000111100 )
b11100101011100110000101011001010 &
b1100001000100000000000011 -
1*
#206
b10001 B
b10001 5
#210
b0 +
b0 8
b100000110001001011001101000001 (
b100000110001001011001101000001 7
b1000101001011100110000110001010 %
b1000101001011100110000110001010 6
0*
#215
b1100101111100110001010011001011 '
b1100101111100110001010011001011 ;
b1100001000100000000000011 .
b10000100001100010000100000001000 -
b0 ,
b100000110001001011001101000001 )
b1000101001011100110000110001010 &
b1100001000100000000000011 "
b1100001000100000000000011 ?
b10000100001100010000100000001000 >
b0 =
b100000110001001011001101000001 <
b1000101001011100110000110001010 :
1*
#216
b10010 B
b10010 5
#220
b11 +
b11 8
b11000100100010100001001010001001 (
b11000100100010100001001010001001 7
b111100001000001111001101111000 %
b111100001000001111001101111000 6
0*
#225
b11111100101010101111001111111001 ;
b11111100101010101111001111111001 '
b11 =
b11000100100010100001001010001001 <
b111100001000001111001101111000 :
b1100101111100110001010011001011 >
b10000100001100010000100000001000 "
b10000100001100010000100000001000 ?
b11 ,
b11000100100010100001001010001001 )
b111100001000001111001101111000 &
b1100101111100110001010011001011 -
b10000100001100010000100000001000 .
1*
#226
b10011 B
b10011 5
#230
b110 +
b110 8
b1100011010010111111100111000110 (
b1100011010010111111100111000110 7
b1011011000000100110010110110110 %
b1011011000000100110010110110110 6
0*
#235
b11000000100110010110110110000000 '
b11000000100110010110110110000000 ;
b1100101111100110001010011001011 .
b11111100101010101111001111111001 -
b110 ,
b1100011010010111111100111000110 )
b1011011000000100110010110110110 &
b1100101111100110001010011001011 "
b1100101111100110001010011001011 ?
b11111100101010101111001111111001 >
b110 =
b1100011010010111111100111000110 <
b1011011000000100110010110110110 :
1*
#236
b10100 B
b10100 5
#240
b11 +
b11 8
b10101000011111101110100101010 (
b10101000011111101110100101010 7
b11011110011101010000001010111100 %
b11011110011101010000001010111100 6
0*
#245
b11011111011111111101111110111110 ;
b11011111011111111101111110111110 '
b11 =
b10101000011111101110100101010 <
b11011110011101010000001010111100 :
b11000000100110010110110110000000 >
b11111100101010101111001111111001 "
b11111100101010101111001111111001 ?
b11 ,
b10101000011111101110100101010 )
b11011110011101010000001010111100 &
b11000000100110010110110110000000 -
b11111100101010101111001111111001 .
1*
#246
b10101 B
b10101 5
#250
b111 +
b111 8
b1000010111100100100000110000101 (
b1000010111100100100000110000101 7
b10111000100101111011111001110001 %
b10111000100101111011111001110001 6
0*
#255
b101110001001011110111110011 '
b101110001001011110111110011 ;
b11000000100110010110110110000000 .
b11011111011111111101111110111110 -
b111 ,
b1000010111100100100000110000101 )
b10111000100101111011111001110001 &
b11000000100110010110110110000000 "
b11000000100110010110110110000000 ?
b11011111011111111101111110111110 >
b111 =
b1000010111100100100000110000101 <
b10111000100101111011111001110001 :
1*
#256
b10110 B
b10110 5
#260
b110 +
b110 8
b11101000001100011001100111010 (
b11101000001100011001100111010 7
b10011101110011000110000000111011 %
b10011101110011000110000000111011 6
0*
#265
b11101100000000000000000000000000 ;
b11101100000000000000000000000000 '
b110 =
b11101000001100011001100111010 <
b10011101110011000110000000111011 :
b101110001001011110111110011 >
b11011111011111111101111110111110 "
b11011111011111111101111110111110 ?
b110 ,
b11101000001100011001100111010 )
b10011101110011000110000000111011 &
b101110001001011110111110011 -
b11011111011111111101111110111110 .
1*
#266
b10111 B
b10111 5
#270
b1 +
b1 8
b1111000110110011001101111110001 (
b1111000110110011001101111110001 7
b1010101010100100101100010101 %
b1010101010100100101100010101 6
0*
#275
b10010001110100001010111100100100 '
b10010001110100001010111100100100 ;
b101110001001011110111110011 .
b11101100000000000000000000000000 -
b1 ,
b1111000110110011001101111110001 )
b1010101010100100101100010101 &
b101110001001011110111110011 "
b101110001001011110111110011 ?
b11101100000000000000000000000000 >
b1 =
b1111000110110011001101111110001 <
b1010101010100100101100010101 :
1*
#276
b11000 B
b11000 5
#280
b111 +
b111 8
b100110001101011111101101001100 (
b100110001101011111101101001100 7
b110001001000110000011101100010 %
b110001001000110000011101100010 6
0*
#285
b110001001000110000 ;
b110001001000110000 '
b111 =
b100110001101011111101101001100 <
b110001001000110000011101100010 :
b10010001110100001010111100100100 >
b11101100000000000000000000000000 "
b11101100000000000000000000000000 ?
b111 ,
b100110001101011111101101001100 )
b110001001000110000011101100010 &
b10010001110100001010111100100100 -
b11101100000000000000000000000000 .
1*
#286
b11001 B
b11001 5
#290
b1111100011011011010100111111000 (
b1111100011011011010100111111000 7
b1000111101110011010000110001111 %
b1000111101110011010000110001111 6
0*
#295
b1000111 '
b1000111 ;
b10010001110100001010111100100100 .
b110001001000110000 -
b1111100011011011010100111111000 )
b1000111101110011010000110001111 &
b10010001110100001010111100100100 "
b10010001110100001010111100100100 ?
b110001001000110000 >
b1111100011011011010100111111000 <
b1000111101110011010000110001111 :
1*
#296
b11010 B
b11010 5
#300
b11 +
b11 8
b10101110011111011001010001011100 (
b10101110011111011001010001011100 7
b11001111110001000101011010011111 %
b11001111110001000101011010011111 6
0*
#305
b11101111111111011101011011011111 ;
b11101111111111011101011011011111 '
b11 =
b10101110011111011001010001011100 <
b11001111110001000101011010011111 :
b1000111 >
b110001001000110000 "
b110001001000110000 ?
b11 ,
b10101110011111011001010001011100 )
b11001111110001000101011010011111 &
b1000111 -
b110001001000110000 .
1*
#306
b11011 B
b11011 5
#310
b0 +
b0 8
b10100100101011100011001001001001 (
b10100100101011100011001001001001 7
b1000100110111100011011110001001 %
b1000100110111100011011110001001 6
0*
#315
b11101001100011000110100111010010 '
b11101001100011000110100111010010 ;
b1000111 .
b11101111111111011101011011011111 -
b0 ,
b10100100101011100011001001001001 )
b1000100110111100011011110001001 &
b1000111 "
b1000111 ?
b11101111111111011101011011011111 >
b0 =
b10100100101011100011001001001001 <
b1000100110111100011011110001001 :
1*
#316
b11100 B
b11100 5
#320
b110 +
b110 8
b10101000110001111111110001010001 (
b10101000110001111111110001010001 7
b11101011111111101100000011010111 %
b11101011111111101100000011010111 6
0*
#325
b10000001101011100000000000000000 ;
b10000001101011100000000000000000 '
b110 =
b10101000110001111111110001010001 <
b11101011111111101100000011010111 :
b11101001100011000110100111010010 >
b11101111111111011101011011011111 "
b11101111111111011101011011011111 ?
b110 ,
b10101000110001111111110001010001 )
b11101011111111101100000011010111 &
b11101001100011000110100111010010 -
b11101111111111011101011011011111 .
1*
#326
b11101 B
b11101 5
#330
b0 +
b0 8
b11100001001011001100111011000010 (
b11100001001011001100111011000010 7
b110000111010111111100001100 %
b110000111010111111100001100 6
0*
#335
b11100111010010100100110111001110 '
b11100111010010100100110111001110 ;
b11101001100011000110100111010010 .
b10000001101011100000000000000000 -
b0 ,
b11100001001011001100111011000010 )
b110000111010111111100001100 &
b11101001100011000110100111010010 "
b11101001100011000110100111010010 ?
b10000001101011100000000000000000 >
b0 =
b11100001001011001100111011000010 <
b110000111010111111100001100 :
1*
#336
b11110 B
b11110 5
#340
b10 +
b10 8
b11110111100101110110100111101 (
b11110111100101110110100111101 7
b10111011100000100101101001110111 %
b10111011100000100101101001110111 6
0*
#345
b11010100000100100100000110101 ;
b11010100000100100100000110101 '
b10 =
b11110111100101110110100111101 <
b10111011100000100101101001110111 :
b11100111010010100100110111001110 >
b10000001101011100000000000000000 "
b10000001101011100000000000000000 ?
b10 ,
b11110111100101110110100111101 )
b10111011100000100101101001110111 &
b11100111010010100100110111001110 -
b10000001101011100000000000000000 .
1*
#346
b11111 B
b11111 5
#350
b1 +
b1 8
b110110111001011000000101101101 (
b110110111001011000000101101101 7
b10111111000001010000000001111110 %
b10111111000001010000000001111110 6
0*
#355
b10001000000111110111111100010001 '
b10001000000111110111111100010001 ;
b11100111010010100100110111001110 .
b11010100000100100100000110101 -
b1 ,
b110110111001011000000101101101 )
b10111111000001010000000001111110 &
b11100111010010100100110111001110 "
b11100111010010100100110111001110 ?
b11010100000100100100000110101 >
b1 =
b110110111001011000000101101101 <
b10111111000001010000000001111110 :
1*
#356
b100000 B
b100000 5
#360
b101 +
b101 8
b11101001111010111111011011010011 (
b11101001111010111111011011010011 7
b1111110100101000111100011111 %
b1111110100101000111100011111 6
0*
#365
b0 ;
b0 '
b101 =
b11101001111010111111011011010011 <
b1111110100101000111100011111 :
b10001000000111110111111100010001 >
b11010100000100100100000110101 "
b11010100000100100100000110101 ?
b101 ,
b11101001111010111111011011010011 )
b1111110100101000111100011111 &
b10001000000111110111111100010001 -
b11010100000100100100000110101 .
1*
#366
b100001 B
b100001 5
#370
b1 +
b1 8
b101101110110100101100101011011 (
b101101110110100101100101011011 7
b10111100000101001000100001111000 %
b10111100000101001000100001111000 6
0*
#375
b10001110001110100010111100011101 '
b10001110001110100010111100011101 ;
b10001000000111110111111100010001 .
b0 -
b1 ,
b101101110110100101100101011011 )
b10111100000101001000100001111000 &
b10001000000111110111111100010001 "
b10001000000111110111111100010001 ?
b0 >
b1 =
b101101110110100101100101011011 <
b10111100000101001000100001111000 :
1*
#376
b100010 B
b100010 5
#380
b0 +
b0 8
b10101000011001010111100101010 (
b10101000011001010111100101010 7
b10011111111100101010111000111111 %
b10011111111100101010111000111111 6
0*
#385
b10110100111111110101110101101001 ;
b10110100111111110101110101101001 '
b0 =
b10101000011001010111100101010 <
b10011111111100101010111000111111 :
b10001110001110100010111100011101 >
b0 "
b0 ?
b0 ,
b10101000011001010111100101010 )
b10011111111100101010111000111111 &
b10001110001110100010111100011101 -
b0 .
1*
#386
b100011 B
b100011 5
#390
b100 +
b100 8
b11000111000110100000110010001110 (
b11000111000110100000110010001110 7
b11000011001111110011100010000110 %
b11000011001111110011100010000110 6
0*
#395
b100001001010011010000001000 '
b100001001010011010000001000 ;
b10001110001110100010111100011101 .
b10110100111111110101110101101001 -
b100 ,
b11000111000110100000110010001110 )
b11000011001111110011100010000110 &
b10001110001110100010111100011101 "
b10001110001110100010111100011101 ?
b10110100111111110101110101101001 >
b100 =
b11000111000110100000110010001110 <
b11000011001111110011100010000110 :
1*
#396
b100100 B
b100100 5
#400
b11 +
b11 8
b10010011011111011011110000100110 (
b10010011011111011011110000100110 7
b1111101001101011001100111111010 %
b1111101001101011001100111111010 6
0*
#405
b11111111011111011011110111111110 ;
b11111111011111011011110111111110 '
b11 =
b10010011011111011011110000100110 <
b1111101001101011001100111111010 :
b100001001010011010000001000 >
b10110100111111110101110101101001 "
b10110100111111110101110101101001 ?
b11 ,
b10010011011111011011110000100110 )
b1111101001101011001100111111010 &
b100001001010011010000001000 -
b10110100111111110101110101101001 .
1*
#406
b100101 B
b100101 5
#410
b10010111100110011010100000101111 (
b10010111100110011010100000101111 7
b11010001100010111011010010100011 %
b11010001100010111011010010100011 6
0*
#415
b11010111100110111011110010101111 '
b11010111100110111011110010101111 ;
b100001001010011010000001000 .
b11111111011111011011110111111110 -
b10010111100110011010100000101111 )
b11010001100010111011010010100011 &
b100001001010011010000001000 "
b100001001010011010000001000 ?
b11111111011111011011110111111110 >
b10010111100110011010100000101111 <
b11010001100010111011010010100011 :
1*
#416
b100110 B
b100110 5
#420
b111 +
b111 8
b100010001010010000110101000100 (
b100010001010010000110101000100 7
b10101111110110000101011001011111 %
b10101111110110000101011001011111 6
0*
#425
b1010111111011000010101100101 ;
b1010111111011000010101100101 '
b111 =
b100010001010010000110101000100 <
b10101111110110000101011001011111 :
b11010111100110111011110010101111 >
b11111111011111011011110111111110 "
b11111111011111011011110111111110 ?
b111 ,
b100010001010010000110101000100 )
b10101111110110000101011001011111 &
b11010111100110111011110010101111 -
b11111111011111011011110111111110 .
1*
#426
b100111 B
b100111 5
#430
b10 +
b10 8
b11110011000010010001101011100110 (
b11110011000010010001101011100110 7
b11100101100110110011011011001011 %
b11100101100110110011011011001011 6
0*
#435
b11100001000010010001001011000010 '
b11100001000010010001001011000010 ;
b11010111100110111011110010101111 .
b1010111111011000010101100101 -
b10 ,
b11110011000010010001101011100110 )
b11100101100110110011011011001011 &
b11010111100110111011110010101111 "
b11010111100110111011110010101111 ?
b1010111111011000010101100101 >
b10 =
b11110011000010010001101011100110 <
b11100101100110110011011011001011 :
1*
#436
b101000 B
b101000 5
#440
b11110110100000101110001011101101 (
b11110110100000101110001011101101 7
b10100110011111100000100101001 %
b10100110011111100000100101001 6
0*
#445
b10100100000101100000000101001 ;
b10100100000101100000000101001 '
b11110110100000101110001011101101 <
b10100110011111100000100101001 :
b11100001000010010001001011000010 >
b1010111111011000010101100101 "
b1010111111011000010101100101 ?
b11110110100000101110001011101101 )
b10100110011111100000100101001 &
b11100001000010010001001011000010 -
b1010111111011000010101100101 .
1*
#446
b101001 B
b101001 5
#450
b111 +
b111 8
b11011010100010101110001010110101 (
b11011010100010101110001010110101 7
b10110010100111111011011001100101 %
b10110010100111111011011001100101 6
0*
#455
b10110010100 '
b10110010100 ;
b11100001000010010001001011000010 .
b10100100000101100000000101001 -
b111 ,
b11011010100010101110001010110101 )
b10110010100111111011011001100101 &
b11100001000010010001001011000010 "
b11100001000010010001001011000010 ?
b10100100000101100000000101001 >
b111 =
b11011010100010101110001010110101 <
b10110010100111111011011001100101 :
1*
#456
b101010 B
b101010 5
#460
b0 +
b0 8
b100010001100011111111101000100 (
b100010001100011111111101000100 7
b111100111100010001100101111001 %
b111100111100010001100101111001 6
0*
#465
b1011111001000110001100010111101 ;
b1011111001000110001100010111101 '
b0 =
b100010001100011111111101000100 <
b111100111100010001100101111001 :
b10110010100 >
b10100100000101100000000101001 "
b10100100000101100000000101001 ?
b0 ,
b100010001100011111111101000100 )
b111100111100010001100101111001 &
b10110010100 -
b10100100000101100000000101001 .
1*
#466
b101011 B
b101011 5
